README.md
setup.cfg
setup.py
sams/__init__.py
sams/default_settings.py
sams/errors.py
sams/logger.py
sams/manage.py
sams/utils.py
sams/api/__init__.py
sams/api/service.py
sams/api/admin/__init__.py
sams/api/admin/sets.py
sams/api/admin/storage_destinations.py
sams/api/consume/__init__.py
sams/api/consume/assets.py
sams/api/consume/sets.py
sams/api/produce/__init__.py
sams/api/produce/assets.py
sams/api/public/__init__.py
sams/api/public/assets.py
sams/apps/__init__.py
sams/apps/api/__init__.py
sams/apps/api/app.py
sams/apps/api/wsgi.py
sams/apps/file_server/__init__.py
sams/apps/file_server/app.py
sams/apps/file_server/settings.py
sams/apps/file_server/wsgi.py
sams/assets/__init__.py
sams/assets/resource.py
sams/assets/service.py
sams/auth/__init__.py
sams/auth/basic.py
sams/auth/decorator.py
sams/auth/public.py
sams/commands/__init__.py
sams/commands/add_renditions_to_existing_assets.py
sams/commands/delete_elastic_index.py
sams/commands/flush_elastic_index.py
sams/commands/index_from_mongo.py
sams/factory/__init__.py
sams/factory/app.py
sams/factory/sentry.py
sams/factory/service.py
sams/sets/__init__.py
sams/sets/resource.py
sams/sets/service.py
sams/storage/__init__.py
sams/storage/destinations.py
sams/storage/sams_media_storage.py
sams/storage/providers/__init__.py
sams/storage/providers/amazon.py
sams/storage/providers/base.py
sams/storage/providers/mongo.py
sams_server.egg-info/PKG-INFO
sams_server.egg-info/SOURCES.txt
sams_server.egg-info/dependency_links.txt
sams_server.egg-info/requires.txt
sams_server.egg-info/top_level.txt